{"6EG41kmvv7xqpBwcm5L92g==":"logo%20alterada%20copy-127x128.png","Ibfyf1jUIjIiS6md1ty08A==":"211a-2000x2000.jpg","LOH3XwTZQ7yV16IGtUpdLw==":"layer%201-265x261.png","VmFmxfUesWDQr8jzInubyA==":"mbr-2000x1334.jpg","x9FdfkbAe1KtvneCO6LQ2A==":"mbr-2000x1333.jpg","InnNBwjmzuZbZoGeX+HzbA==":"mbr-2000x1221.jpg","zG5VAgleDo1WSILagLHgKQ==":"mbr-1-2000x1333.jpg","yFka53lQFI62vft7JnRKLw==":"mbr-2-2000x1333.jpg","zSDRSqD/9wKNNx003SxgjQ==":"mbr-2000x1250.jpg","X8gzktjlFWvvo0uzt/CEJA==":"mbr-600x400.jpg","JGQ/+NMDNBKIUZZkgldeVg==":"mbr-600x825.jpg","J6t7tGRMLFWSo1J3GjwCjA==":"mbr-600x450.jpg","GCNG3gOlG6iZv8v7KfiguA==":"mbr-1-600x400.jpg","3DZJshjPhwARBvCyUvYjng==":"coworkers-600x399.jpg","sJsCVGDMTTTGc/XG1ovCyw==":"1-600x399.jpg","V7AkujNyzBuQ3PoFyY0gxw==":"2-600x399.jpg","ZJE8JbfxYHtKUEujSuuYEw==":"3-600x399.jpg","zyzzpza8SDlP0U89Em/uzQ==":"sem%20t%C3%ADtulo-600x600.jpg","+4nW3SjFDKBd73nG6qqJ/g==":"sem%20t%C3%ADtulo-600x600.jpg","pJcmi9Vg1CvxZTk1bMnIEQ==":"sem%20t%C3%ADtulo-600x600.jpg","7f5eqVvR0yt5SYOjglNH/Q==":"sem%20t%C3%ADtulo-600x600.jpg","qzDuFyF5d87EZ567mJYZ4w==":"mbr-2000x3000.jpg","++wMFG1d6RVimfixVeQgGw==":"mbr-1-2000x1334.jpg","ey+BBnVx5MLLNzzQdygg3Q==":"1-min-2000x2255.png","J92drPTSIyrUb+IIuQ7h1g==":"mbr-3-2000x1333.jpg","5k1Hvwxd7aPKY4iAD8euqA==":"mbr-2-600x400.jpg","X5mvGhjgc2HFwYpQouEiiw==":"mbr-600x418.jpg","tuzTCZ71AlsvxtssoJ55XQ==":"mbr-600x399.jpg","B/OvpfSU1wAQCVhNeOXbTA==":"mbr-600x371.jpg","Xm0aNbd4fXinbGGbvngUHg==":"mbr-4-2000x1333.jpg","jWyRU4/v+TtOnQuQ8Wb6HA==":"origami%20i%20g-2000x1333.jpg","DImMHQLE8BT9kkaIuzKLTg==":"losango%20liso-2000x1333.jpg","bzEYlPsmn+Zs/xGXQDJ9tw==":"losango%20relevo-2000x1333.jpg","V3SYxnV+qFFKoa24VB36kg==":"diamante-2000x1333.jpg","GrU9fmGfl6J0Aj3Ja9KbLQ==":"placa%20retangular-2000x1333.jpg","5rtLY8bGt67fQGEK0QMSJw==":"flower-600x518.jpg","rNkIRZnJGY+WMlKxKBbA/A==":"001%20-%20flower-min-2000x2803.png","hd+WP/RxK2sFutCuk525cg==":"051-052%20-sinapsys-min-2000x2803.png","3gNV83lC70ndeHm05Ron6A==":"065%20-%20origami%20ii-min-2000x2803.png","YcCXECuNi/5NZHLWvzIDKQ==":"035-%20squadri-min-2000x2803.png","RaoE35Xi+2yGFmoHhHXjow==":"054-h%C3%A9lices-min-2000x2803.png","qW00sV9A35Q77J3uhYYcFw==":"mbr-3-600x400.jpg","t4f7G/kl/vABUiAkLIMGZg==":"mbr-1-600x418.jpg","p3j5jF3odn0ToUonjEJIdQ==":"mbr-4-600x400.jpg","gpsBqy60BDnU52I8DrparQ==":"mbrs-600x400.jpg","8YzktIOfiEAoRpQPMs+qTQ==":"mbr-2-600x418.jpg","hYrOlyE5nSy/CkgjaTUy6w==":"mbr-5-600x400.jpg","7vVxL+nfnYSoQh722U9+xw==":"035-squadri-min-2000x1061.png","oxofvaqtQZSasmenr8vHww==":"054-hlices-min-2000x1055.png","Aym89xs7J68RachknySy3g==":"065-origami-ii-min-2000x1061.png","m5/a7h7P+GFRkDzpwzViow==":"001-flower-min-2000x1064.png","77g3DiIiNFN5NLpwC2ilNA==":"mbr-5-2000x1333.jpg","qjmC/viPdVRGYV8p5JGt5w==":"mbr-2000x1500.jpg","MxtPKFPb5zoPxiqwzH+wKw==":"mbr-6-2000x1333.jpg","9YknO/CLfN3aad1mk0Ei/g==":"mbr-2000x1330.jpg","0Zzfah5v6zwz0H19qqj/cg==":"mbr-7-2000x1333.jpg","n6EXA1ZUxLOc0KayqZ38Bg==":"wp_20150528_11_52_22_pro-2000x1125.jpg","1XWprc+J4uwv08ctO1pHIg==":"2015-06-23-600x450.jpg","RGGgDXYRp02awN6zyiJ8Hg==":"ecomadeira-600x451.jpg","25JsLjD2lmSIhO56KHvqwg==":"ecomadeira-600x399.jpg","ToWjRZHzi7VHBB7HY6Eslg==":"vazado-600x399.jpg","cBDyk/Eb3vbEKtxMsHtneA==":"nil-160x160.png","7JXrt/PQkzdMyzbWZsViJg==":"daniel%201%20-160x158.jpg","FGe4wxNuQoFjfcuJcEQ+8g==":"ana-160x160.jpg","rSdI4RVj8IIKJFkkpkEsWg==":"juan-149x160.jpg","HNgZ5XYja16E2DvsXGQbdw==":"oto-149x160.jpg","qY+ftRxrJU7QryQEkz0O0A==":"ramires-114x160.jpg","c2cViCPGaTu385HZHhcX7g==":"vazados-2000x1413.jpg","65O1lUkrI8x8Tv19z3lF/w==":"vazados-2000x1332.jpg","xJL+8A55+L1mlf1NDzQ6Yg==":"3-2000x1333.jpg","XXvXNFPvRh2m1BM9Hn2lig==":"vazados-2000x657.jpg","oETNAMllfpfjVdSUSHg6Og==":"cobogos-2000x657.jpg","hhDyU6ri4F3Ojf9Npa8Kng==":"cobogos-2000x731.jpg","DhPqp+vCByIYnWLDOVixBg==":"cobogos-1-2000x731.jpg","7oLvIYQMduP+dUPNI3qeXA==":"flower-2000x1332.png","q9/PH2Xs+9jonoPoNArGBg==":"origam%20ii-2000x1332.jpg","DfXzcsUTTLfimjlyL63ugw==":"diamante-2000x1332.jpg","Eif1sxXDc2hqoaLh9va2Hg==":"placa%20retangular-2000x2803.png","9jz8sF4XAddM5XDuGmWAFw==":"placa%20retangular-2000x1332.png","rGh+DJx4qPVDmOejvUd3Fw==":"scaleno-2000x1332.png","JV8XGlFScB+lqFe+oNqR7g==":"squadri-2000x1332.png","puqzxlpovryWgzTU1twMSQ==":"favo-2000x1332.png","pyeNVVdonNZcLrVaDZQ1PQ==":"ariete-2000x1332.jpg","CLZfeghtHYDEs6SNJCT6qg==":"origami-2000x1415.png","Bu/zaGdgfNL5DGVHHRiIiw==":"flower-2000x1332-800x532.png","4j9E3lqpy1hYHs3cMhZESA==":"origam-ii-2000x1332-800x532.jpg","ay38g+siLd4lv8GNqj6h2Q==":"favo-2000x1332-800x532.png","U9RTrEnMFNCCvm/15V0GrQ==":"scaleno-2000x1332.png","euTtbJITIoXfkCYnB+IVPQ==":"mbr-1654x625.jpg","ys5dyNM5jy7l006ZJxinXA==":"mbr-1-1654x625.jpg"}